{"cameraMode":{"drawMode":0,"name":"Shaded","section":"Shading Mode"},"sceneLighting":true,"audioPlay":false,"sceneViewState":{"m_AlwaysRefresh":false,"showFog":true,"showSkybox":true,"showFlares":true,"showImageEffects":true,"showParticleSystems":true,"showVisualEffectGraphs":true,"m_FxEnabled":true},"in2DMode":false,"pivot":{"x":-16.993738174438478,"y":-3.059628963470459,"z":-13.126315116882325},"rotation":{"x":-0.06055011227726936,"y":0.8746516704559326,"z":-0.11540962010622025,"w":-0.4670370817184448},"size":10.449999809265137,"orthographic":false}